test_brainai/brainai/__init__.py
test_brainai/brainai/_openai_scripts.py
test_brainai/brainai/api_requestor.py
test_brainai/brainai/brainai_object.py
test_brainai/brainai/brainai_response.py
test_brainai/brainai/cli.py
test_brainai/brainai/embeddings_utils.py
test_brainai/brainai/error.py
test_brainai/brainai/object_classes.py
test_brainai/brainai/py.typed
test_brainai/brainai/upload_progress.py
test_brainai/brainai/util.py
test_brainai/brainai/validators.py
test_brainai/brainai/version.py
test_brainai/brainai/wandb_logger.py
test_brainai/brainai/api_resources/__init__.py
test_brainai/brainai/api_resources/audio.py
test_brainai/brainai/api_resources/brainos_completion.py
test_brainai/brainai/api_resources/chat_completion.py
test_brainai/brainai/api_resources/completion.py
test_brainai/brainai/api_resources/customer.py
test_brainai/brainai/api_resources/deployment.py
test_brainai/brainai/api_resources/edit.py
test_brainai/brainai/api_resources/embedding.py
test_brainai/brainai/api_resources/engine.py
test_brainai/brainai/api_resources/error_object.py
test_brainai/brainai/api_resources/file.py
test_brainai/brainai/api_resources/fine_tune.py
test_brainai/brainai/api_resources/fine_tuning.py
test_brainai/brainai/api_resources/image.py
test_brainai/brainai/api_resources/model.py
test_brainai/brainai/api_resources/moderation.py
test_brainai/brainai/api_resources/abstract/__init__.py
test_brainai/brainai/api_resources/abstract/api_resource.py
test_brainai/brainai/api_resources/abstract/createable_api_resource.py
test_brainai/brainai/api_resources/abstract/deletable_api_resource.py
test_brainai/brainai/api_resources/abstract/engine_api_resource.py
test_brainai/brainai/api_resources/abstract/listable_api_resource.py
test_brainai/brainai/api_resources/abstract/nested_resource_class_methods.py
test_brainai/brainai/api_resources/abstract/paginatable_api_resource.py
test_brainai/brainai/api_resources/abstract/updateable_api_resource.py
pyTestBrainai-1.4.0.0.dist-info/LICENSE
pyTestBrainai-1.4.0.0.dist-info/METADATA
pyTestBrainai-1.4.0.0.dist-info/WHEEL
pyTestBrainai-1.4.0.0.dist-info/top_level.txt
pyTestBrainai-1.4.0.0.dist-info/RECORD
